<?xml version="1.0" encoding="utf-8"?>
<languages>
  <language>
    <code>aa</code>
    <name>afarski</name>
  </language>
  <language>
    <code>ab</code>
    <name>abkazijski</name>
  </language>
  <language>
    <code>ace</code>
    <name>ačineski</name>
  </language>
  <language>
    <code>ach</code>
    <name>akoli</name>
  </language>
  <language>
    <code>ada</code>
    <name>adangmejski</name>
  </language>
  <language>
    <code>ady</code>
    <name>adigejski</name>
  </language>
  <language>
    <code>ae</code>
    <name>avestanski</name>
  </language>
  <language>
    <code>af</code>
    <name>afrikanerski</name>
  </language>
  <language>
    <code>afa</code>
    <name>afro-azijatski</name>
  </language>
  <language>
    <code>afh</code>
    <name>afrihili</name>
  </language>
  <language>
    <code>ain</code>
    <name>ainu</name>
  </language>
  <language>
    <code>ak</code>
    <name>akan</name>
  </language>
  <language>
    <code>akk</code>
    <name>akadijski</name>
  </language>
  <language>
    <code>ale</code>
    <name>aljut</name>
  </language>
  <language>
    <code>alg</code>
    <name>algonkvijanski jezik</name>
  </language>
  <language>
    <code>alt</code>
    <name>južni altai</name>
  </language>
  <language>
    <code>am</code>
    <name>amharski</name>
  </language>
  <language>
    <code>an</code>
    <name>aragonežanski</name>
  </language>
  <language>
    <code>ang</code>
    <name>staroengleski</name>
  </language>
  <language>
    <code>anp</code>
    <name>angika</name>
  </language>
  <language>
    <code>apa</code>
    <name>apački jezik</name>
  </language>
  <language>
    <code>ar</code>
    <name>arapski</name>
  </language>
  <language>
    <code>arc</code>
    <name>armajski</name>
  </language>
  <language>
    <code>arn</code>
    <name>arokanijski</name>
  </language>
  <language>
    <code>arp</code>
    <name>arapaho</name>
  </language>
  <language>
    <code>art</code>
    <name>veštački</name>
  </language>
  <language>
    <code>arw</code>
    <name>aravak</name>
  </language>
  <language>
    <code>as</code>
    <name>asemijski</name>
  </language>
  <language>
    <code>ast</code>
    <name>asturijski</name>
  </language>
  <language>
    <code>ath</code>
    <name>atapaskan</name>
  </language>
  <language>
    <code>aus</code>
    <name>australijski jezik</name>
  </language>
  <language>
    <code>av</code>
    <name>avarski</name>
  </language>
  <language>
    <code>awa</code>
    <name>avadhi</name>
  </language>
  <language>
    <code>ay</code>
    <name>ajmara</name>
  </language>
  <language>
    <code>az</code>
    <name>azerbejdžanski</name>
  </language>
  <language>
    <code>ba</code>
    <name>baškir</name>
  </language>
  <language>
    <code>bad</code>
    <name>banda</name>
  </language>
  <language>
    <code>bai</code>
    <name>bamileke</name>
  </language>
  <language>
    <code>bal</code>
    <name>baluči</name>
  </language>
  <language>
    <code>ban</code>
    <name>balinezijski</name>
  </language>
  <language>
    <code>bas</code>
    <name>basa</name>
  </language>
  <language>
    <code>bat</code>
    <name>baltički jezik</name>
  </language>
  <language>
    <code>be</code>
    <name>beloruski</name>
  </language>
  <language>
    <code>bej</code>
    <name>beja</name>
  </language>
  <language>
    <code>bem</code>
    <name>bemba</name>
  </language>
  <language>
    <code>ber</code>
    <name>berber</name>
  </language>
  <language>
    <code>bg</code>
    <name>bugarski</name>
  </language>
  <language>
    <code>bh</code>
    <name>biharski</name>
  </language>
  <language>
    <code>bho</code>
    <name>bojpuri</name>
  </language>
  <language>
    <code>bi</code>
    <name>bislama</name>
  </language>
  <language>
    <code>bik</code>
    <name>bikol</name>
  </language>
  <language>
    <code>bin</code>
    <name>bini</name>
  </language>
  <language>
    <code>bla</code>
    <name>siksika</name>
  </language>
  <language>
    <code>bm</code>
    <name>bambara</name>
  </language>
  <language>
    <code>bn</code>
    <name>bengalski</name>
  </language>
  <language>
    <code>bnt</code>
    <name>bantu</name>
  </language>
  <language>
    <code>bo</code>
    <name>tibetanski</name>
  </language>
  <language>
    <code>br</code>
    <name>bretonski</name>
  </language>
  <language>
    <code>bra</code>
    <name>braj</name>
  </language>
  <language>
    <code>bs</code>
    <name>bosanski</name>
  </language>
  <language>
    <code>btk</code>
    <name>batak</name>
  </language>
  <language>
    <code>bua</code>
    <name>buriat</name>
  </language>
  <language>
    <code>bug</code>
    <name>buginežanskii</name>
  </language>
  <language>
    <code>byn</code>
    <name>blin</name>
  </language>
  <language>
    <code>ca</code>
    <name>katalonski</name>
  </language>
  <language>
    <code>cad</code>
    <name>kado</name>
  </language>
  <language>
    <code>cai</code>
    <name>jezik centralno-američkih indijanaca</name>
  </language>
  <language>
    <code>car</code>
    <name>karipski</name>
  </language>
  <language>
    <code>cau</code>
    <name>kavkaski</name>
  </language>
  <language>
    <code>cch</code>
    <name>atsam</name>
  </language>
  <language>
    <code>ce</code>
    <name>čečenski</name>
  </language>
  <language>
    <code>ceb</code>
    <name>cebuano</name>
  </language>
  <language>
    <code>cel</code>
    <name>keltski jezik</name>
  </language>
  <language>
    <code>ch</code>
    <name>čamoro</name>
  </language>
  <language>
    <code>chb</code>
    <name>čibča</name>
  </language>
  <language>
    <code>chg</code>
    <name>čagatai</name>
  </language>
  <language>
    <code>chk</code>
    <name>čukeski</name>
  </language>
  <language>
    <code>chm</code>
    <name>mari</name>
  </language>
  <language>
    <code>chn</code>
    <name>činukski</name>
  </language>
  <language>
    <code>cho</code>
    <name>čoktavski</name>
  </language>
  <language>
    <code>chp</code>
    <name>čipvijanski</name>
  </language>
  <language>
    <code>chr</code>
    <name>čeroki</name>
  </language>
  <language>
    <code>chy</code>
    <name>čejenski</name>
  </language>
  <language>
    <code>cmc</code>
    <name>čamski jezik</name>
  </language>
  <language>
    <code>co</code>
    <name>korzikanski</name>
  </language>
  <language>
    <code>cop</code>
    <name>koptski</name>
  </language>
  <language>
    <code>cpe</code>
    <name>kreolski ili pidžin zasnovan na engleskom</name>
  </language>
  <language>
    <code>cpf</code>
    <name>kreolski ili pidžin zasnovan na francuskom</name>
  </language>
  <language>
    <code>cpp</code>
    <name>kreolski ili pidžin baziran na portugalskom</name>
  </language>
  <language>
    <code>cr</code>
    <name>kri</name>
  </language>
  <language>
    <code>crh</code>
    <name>krimeanski turski</name>
  </language>
  <language>
    <code>crp</code>
    <name>kreolski ili pidžin</name>
  </language>
  <language>
    <code>cs</code>
    <name>češki</name>
  </language>
  <language>
    <code>csb</code>
    <name>kašubijanski</name>
  </language>
  <language>
    <code>cu</code>
    <name>staroslovenski</name>
  </language>
  <language>
    <code>cus</code>
    <name>kušitički jezik</name>
  </language>
  <language>
    <code>cv</code>
    <name>čuvaški</name>
  </language>
  <language>
    <code>cy</code>
    <name>velški</name>
  </language>
  <language>
    <code>da</code>
    <name>danski</name>
  </language>
  <language>
    <code>dak</code>
    <name>dakota</name>
  </language>
  <language>
    <code>dar</code>
    <name>dargva</name>
  </language>
  <language>
    <code>day</code>
    <name>dajaški</name>
  </language>
  <language>
    <code>de</code>
    <name>njemački</name>
  </language>
  <language>
    <code>del</code>
    <name>delaver</name>
  </language>
  <language>
    <code>den</code>
    <name>slavski</name>
  </language>
  <language>
    <code>dgr</code>
    <name>dogrib</name>
  </language>
  <language>
    <code>din</code>
    <name>dinka</name>
  </language>
  <language>
    <code>doi</code>
    <name>dogri</name>
  </language>
  <language>
    <code>dra</code>
    <name>dravidijski jezik</name>
  </language>
  <language>
    <code>dsb</code>
    <name>niski sorbijanski</name>
  </language>
  <language>
    <code>dua</code>
    <name>duala</name>
  </language>
  <language>
    <code>dum</code>
    <name>srednji holandski</name>
  </language>
  <language>
    <code>dv</code>
    <name>divehijski</name>
  </language>
  <language>
    <code>dyu</code>
    <name>đula</name>
  </language>
  <language>
    <code>dz</code>
    <name>džonga</name>
  </language>
  <language>
    <code>ee</code>
    <name>eve</name>
  </language>
  <language>
    <code>efi</code>
    <name>efikski</name>
  </language>
  <language>
    <code>egy</code>
    <name>staroegipatski</name>
  </language>
  <language>
    <code>eka</code>
    <name>ekajuk</name>
  </language>
  <language>
    <code>el</code>
    <name>grčki</name>
  </language>
  <language>
    <code>elx</code>
    <name>elamitski</name>
  </language>
  <language>
    <code>en</code>
    <name>engleski</name>
  </language>
  <language>
    <code>enm</code>
    <name>srednji engleski</name>
  </language>
  <language>
    <code>eo</code>
    <name>esperanto</name>
  </language>
  <language>
    <code>es</code>
    <name>španjolski</name>
  </language>
  <language>
    <code>et</code>
    <name>estonski</name>
  </language>
  <language>
    <code>eu</code>
    <name>baskijski</name>
  </language>
  <language>
    <code>ewo</code>
    <name>evondo</name>
  </language>
  <language>
    <code>fa</code>
    <name>persijski</name>
  </language>
  <language>
    <code>fan</code>
    <name>fang</name>
  </language>
  <language>
    <code>fat</code>
    <name>fanti</name>
  </language>
  <language>
    <code>ff</code>
    <name>fulah</name>
  </language>
  <language>
    <code>fi</code>
    <name>finski</name>
  </language>
  <language>
    <code>fil</code>
    <name>filipinski</name>
  </language>
  <language>
    <code>fiu</code>
    <name>ugro-finski jezik</name>
  </language>
  <language>
    <code>fj</code>
    <name>fidžijski</name>
  </language>
  <language>
    <code>fo</code>
    <name>farski</name>
  </language>
  <language>
    <code>fon</code>
    <name>fon</name>
  </language>
  <language>
    <code>fr</code>
    <name>francuski</name>
  </language>
  <language>
    <code>frm</code>
    <name>srednji francuski</name>
  </language>
  <language>
    <code>fro</code>
    <name>starofrancuski</name>
  </language>
  <language>
    <code>frr</code>
    <name>severno-frizijski</name>
  </language>
  <language>
    <code>frs</code>
    <name>istočni frizijski</name>
  </language>
  <language>
    <code>fur</code>
    <name>friulijski</name>
  </language>
  <language>
    <code>fy</code>
    <name>frizijski</name>
  </language>
  <language>
    <code>ga</code>
    <name>irski</name>
  </language>
  <language>
    <code>gaa</code>
    <name>ga</name>
  </language>
  <language>
    <code>gay</code>
    <name>gajo</name>
  </language>
  <language>
    <code>gba</code>
    <name>gbaja</name>
  </language>
  <language>
    <code>gd</code>
    <name>škotski galski</name>
  </language>
  <language>
    <code>gem</code>
    <name>germanski jezik</name>
  </language>
  <language>
    <code>gez</code>
    <name>džiz</name>
  </language>
  <language>
    <code>gil</code>
    <name>gilbertški</name>
  </language>
  <language>
    <code>gl</code>
    <name>galski</name>
  </language>
  <language>
    <code>gmh</code>
    <name>srednji visoki nemački</name>
  </language>
  <language>
    <code>gn</code>
    <name>gvarani</name>
  </language>
  <language>
    <code>goh</code>
    <name>staronemački</name>
  </language>
  <language>
    <code>gon</code>
    <name>gondi</name>
  </language>
  <language>
    <code>gor</code>
    <name>gorontalo</name>
  </language>
  <language>
    <code>got</code>
    <name>gotski</name>
  </language>
  <language>
    <code>grb</code>
    <name>grebo</name>
  </language>
  <language>
    <code>grc</code>
    <name>starogrčki</name>
  </language>
  <language>
    <code>gsw</code>
    <name>švajcarsko nemački</name>
  </language>
  <language>
    <code>gu</code>
    <name>gudžarati</name>
  </language>
  <language>
    <code>gv</code>
    <name>manks</name>
  </language>
  <language>
    <code>ha</code>
    <name>hausa</name>
  </language>
  <language>
    <code>hai</code>
    <name>haida</name>
  </language>
  <language>
    <code>haw</code>
    <name>havajski</name>
  </language>
  <language>
    <code>he</code>
    <name>hebrejski</name>
  </language>
  <language>
    <code>hi</code>
    <name>hindi</name>
  </language>
  <language>
    <code>hil</code>
    <name>hiligajnon</name>
  </language>
  <language>
    <code>him</code>
    <name>himačali</name>
  </language>
  <language>
    <code>hit</code>
    <name>hitite</name>
  </language>
  <language>
    <code>hmn</code>
    <name>hmong</name>
  </language>
  <language>
    <code>ho</code>
    <name>hiri motu</name>
  </language>
  <language>
    <code>hr</code>
    <name>hrvatski</name>
  </language>
  <language>
    <code>hsb</code>
    <name>gornji sorbijski</name>
  </language>
  <language>
    <code>ht</code>
    <name>haićanski</name>
  </language>
  <language>
    <code>hu</code>
    <name>mađarski</name>
  </language>
  <language>
    <code>hup</code>
    <name>hupa</name>
  </language>
  <language>
    <code>hy</code>
    <name>jermenski</name>
  </language>
  <language>
    <code>hz</code>
    <name>herero</name>
  </language>
  <language>
    <code>ia</code>
    <name>interlingva</name>
  </language>
  <language>
    <code>iba</code>
    <name>iban</name>
  </language>
  <language>
    <code>id</code>
    <name>indonezijski</name>
  </language>
  <language>
    <code>ie</code>
    <name>interlingve</name>
  </language>
  <language>
    <code>ig</code>
    <name>igbo</name>
  </language>
  <language>
    <code>ii</code>
    <name>sičuan ji</name>
  </language>
  <language>
    <code>ijo</code>
    <name>ijo</name>
  </language>
  <language>
    <code>ik</code>
    <name>inupiak</name>
  </language>
  <language>
    <code>ilo</code>
    <name>iloko</name>
  </language>
  <language>
    <code>inc</code>
    <name>indik</name>
  </language>
  <language>
    <code>ine</code>
    <name>indo-evropski jezik</name>
  </language>
  <language>
    <code>inh</code>
    <name>ingušetski</name>
  </language>
  <language>
    <code>io</code>
    <name>ido</name>
  </language>
  <language>
    <code>ira</code>
    <name>iranski jezik</name>
  </language>
  <language>
    <code>iro</code>
    <name>irokvojanski</name>
  </language>
  <language>
    <code>is</code>
    <name>islandski</name>
  </language>
  <language>
    <code>it</code>
    <name>talijanski</name>
  </language>
  <language>
    <code>iu</code>
    <name>inuktitut</name>
  </language>
  <language>
    <code>ja</code>
    <name>japanski</name>
  </language>
  <language>
    <code>jbo</code>
    <name>lojban</name>
  </language>
  <language>
    <code>jpr</code>
    <name>judeo-persijski</name>
  </language>
  <language>
    <code>jrb</code>
    <name>judeo-arapski</name>
  </language>
  <language>
    <code>jv</code>
    <name>javanski</name>
  </language>
  <language>
    <code>ka</code>
    <name>gruzijski</name>
  </language>
  <language>
    <code>kaa</code>
    <name>kara-kalpaški</name>
  </language>
  <language>
    <code>kab</code>
    <name>kabile</name>
  </language>
  <language>
    <code>kac</code>
    <name>kačin</name>
  </language>
  <language>
    <code>kaj</code>
    <name>žju</name>
  </language>
  <language>
    <code>kam</code>
    <name>kamba</name>
  </language>
  <language>
    <code>kar</code>
    <name>karenski</name>
  </language>
  <language>
    <code>kaw</code>
    <name>kavi</name>
  </language>
  <language>
    <code>kbd</code>
    <name>kabardijski</name>
  </language>
  <language>
    <code>kcg</code>
    <name>tjap</name>
  </language>
  <language>
    <code>kfo</code>
    <name>koro</name>
  </language>
  <language>
    <code>kg</code>
    <name>kongo</name>
  </language>
  <language>
    <code>kha</code>
    <name>kasi</name>
  </language>
  <language>
    <code>khi</code>
    <name>koisanski jezik</name>
  </language>
  <language>
    <code>kho</code>
    <name>kotanizijski</name>
  </language>
  <language>
    <code>ki</code>
    <name>kikuju</name>
  </language>
  <language>
    <code>kj</code>
    <name>kuanjama</name>
  </language>
  <language>
    <code>kk</code>
    <name>kozački</name>
  </language>
  <language>
    <code>kl</code>
    <name>kalalisutski</name>
  </language>
  <language>
    <code>km</code>
    <name>kmerski</name>
  </language>
  <language>
    <code>kmb</code>
    <name>kimbundu</name>
  </language>
  <language>
    <code>kn</code>
    <name>kanada</name>
  </language>
  <language>
    <code>ko</code>
    <name>korejski</name>
  </language>
  <language>
    <code>kok</code>
    <name>konkani</name>
  </language>
  <language>
    <code>kos</code>
    <name>kosreanski</name>
  </language>
  <language>
    <code>kpe</code>
    <name>kpele</name>
  </language>
  <language>
    <code>kr</code>
    <name>kanuri</name>
  </language>
  <language>
    <code>krc</code>
    <name>karačaj-balkar</name>
  </language>
  <language>
    <code>krl</code>
    <name>karelijski</name>
  </language>
  <language>
    <code>kro</code>
    <name>kru</name>
  </language>
  <language>
    <code>kru</code>
    <name>kurukh</name>
  </language>
  <language>
    <code>ks</code>
    <name>kašmiri</name>
  </language>
  <language>
    <code>ku</code>
    <name>kurdski</name>
  </language>
  <language>
    <code>kum</code>
    <name>kumik</name>
  </language>
  <language>
    <code>kut</code>
    <name>kutenai</name>
  </language>
  <language>
    <code>kv</code>
    <name>komi</name>
  </language>
  <language>
    <code>kw</code>
    <name>korniški</name>
  </language>
  <language>
    <code>ky</code>
    <name>kirgiski</name>
  </language>
  <language>
    <code>la</code>
    <name>latinski</name>
  </language>
  <language>
    <code>lad</code>
    <name>ladino</name>
  </language>
  <language>
    <code>lah</code>
    <name>landa</name>
  </language>
  <language>
    <code>lam</code>
    <name>lamba</name>
  </language>
  <language>
    <code>lb</code>
    <name>luksemburški</name>
  </language>
  <language>
    <code>lez</code>
    <name>lezgian</name>
  </language>
  <language>
    <code>lg</code>
    <name>ganda</name>
  </language>
  <language>
    <code>li</code>
    <name>limburgiš</name>
  </language>
  <language>
    <code>ln</code>
    <name>lingala</name>
  </language>
  <language>
    <code>lo</code>
    <name>laoški</name>
  </language>
  <language>
    <code>lol</code>
    <name>mongo</name>
  </language>
  <language>
    <code>loz</code>
    <name>lozi</name>
  </language>
  <language>
    <code>lt</code>
    <name>litvanski</name>
  </language>
  <language>
    <code>lu</code>
    <name>luba-katanga</name>
  </language>
  <language>
    <code>lua</code>
    <name>luba-lulua</name>
  </language>
  <language>
    <code>lui</code>
    <name>luiseno</name>
  </language>
  <language>
    <code>lun</code>
    <name>lunda</name>
  </language>
  <language>
    <code>luo</code>
    <name>luo</name>
  </language>
  <language>
    <code>lus</code>
    <name>lušai</name>
  </language>
  <language>
    <code>lv</code>
    <name>letonski</name>
  </language>
  <language>
    <code>mad</code>
    <name>madureški</name>
  </language>
  <language>
    <code>mag</code>
    <name>magahi</name>
  </language>
  <language>
    <code>mai</code>
    <name>maitili</name>
  </language>
  <language>
    <code>mak</code>
    <name>makasar</name>
  </language>
  <language>
    <code>man</code>
    <name>mandingo</name>
  </language>
  <language>
    <code>map</code>
    <name>austronežanski</name>
  </language>
  <language>
    <code>mas</code>
    <name>masai</name>
  </language>
  <language>
    <code>mdf</code>
    <name>mokša</name>
  </language>
  <language>
    <code>mdr</code>
    <name>mandar</name>
  </language>
  <language>
    <code>men</code>
    <name>mende</name>
  </language>
  <language>
    <code>mg</code>
    <name>malagazijski</name>
  </language>
  <language>
    <code>mga</code>
    <name>srednji irski</name>
  </language>
  <language>
    <code>mh</code>
    <name>maršalski</name>
  </language>
  <language>
    <code>mi</code>
    <name>maorski</name>
  </language>
  <language>
    <code>mic</code>
    <name>mikmak</name>
  </language>
  <language>
    <code>min</code>
    <name>minangkabau</name>
  </language>
  <language>
    <code>mis</code>
    <name>razni jezici</name>
  </language>
  <language>
    <code>mk</code>
    <name>makedonski</name>
  </language>
  <language>
    <code>mkh</code>
    <name>mon-kmerski jezik</name>
  </language>
  <language>
    <code>ml</code>
    <name>malajalam</name>
  </language>
  <language>
    <code>mn</code>
    <name>mongolski</name>
  </language>
  <language>
    <code>mnc</code>
    <name>manču</name>
  </language>
  <language>
    <code>mni</code>
    <name>manipuri</name>
  </language>
  <language>
    <code>mno</code>
    <name>manobo jezik</name>
  </language>
  <language>
    <code>mo</code>
    <name>moldavski</name>
  </language>
  <language>
    <code>moh</code>
    <name>mahavski</name>
  </language>
  <language>
    <code>mos</code>
    <name>mosi</name>
  </language>
  <language>
    <code>mr</code>
    <name>marati</name>
  </language>
  <language>
    <code>ms</code>
    <name>malajski</name>
  </language>
  <language>
    <code>mt</code>
    <name>melteški</name>
  </language>
  <language>
    <code>mul</code>
    <name>više jezika</name>
  </language>
  <language>
    <code>mun</code>
    <name>munda jezik</name>
  </language>
  <language>
    <code>mus</code>
    <name>kriški</name>
  </language>
  <language>
    <code>mwl</code>
    <name>mirandeški</name>
  </language>
  <language>
    <code>mwr</code>
    <name>marvari</name>
  </language>
  <language>
    <code>my</code>
    <name>burmanski</name>
  </language>
  <language>
    <code>myn</code>
    <name>majanski jezik</name>
  </language>
  <language>
    <code>myv</code>
    <name>erzija</name>
  </language>
  <language>
    <code>na</code>
    <name>nauru</name>
  </language>
  <language>
    <code>nah</code>
    <name>nahuatl</name>
  </language>
  <language>
    <code>nai</code>
    <name>jezik severno-američkih indijanaca</name>
  </language>
  <language>
    <code>nap</code>
    <name>neapolitanski</name>
  </language>
  <language>
    <code>nb</code>
    <name>norveški bokmål</name>
  </language>
  <language>
    <code>nd</code>
    <name>severni ndebele</name>
  </language>
  <language>
    <code>nds</code>
    <name>niski nemački</name>
  </language>
  <language>
    <code>ne</code>
    <name>nepalski</name>
  </language>
  <language>
    <code>new</code>
    <name>nevari</name>
  </language>
  <language>
    <code>ng</code>
    <name>ndonga</name>
  </language>
  <language>
    <code>nia</code>
    <name>nias</name>
  </language>
  <language>
    <code>nic</code>
    <name>niger-kordofanijski jezik</name>
  </language>
  <language>
    <code>niu</code>
    <name>niuean</name>
  </language>
  <language>
    <code>nl</code>
    <name>holandski</name>
  </language>
  <language>
    <code>nl_BE</code>
    <name>flamanski</name>
  </language>
  <language>
    <code>nn</code>
    <name>norveški njorsk</name>
  </language>
  <language>
    <code>no</code>
    <name>norveški</name>
  </language>
  <language>
    <code>nog</code>
    <name>nogai</name>
  </language>
  <language>
    <code>non</code>
    <name>stari norski</name>
  </language>
  <language>
    <code>nqo</code>
    <name>n’ko</name>
  </language>
  <language>
    <code>nr</code>
    <name>južni ndebele</name>
  </language>
  <language>
    <code>nso</code>
    <name>severni soto</name>
  </language>
  <language>
    <code>nub</code>
    <name>nubijski jezik</name>
  </language>
  <language>
    <code>nv</code>
    <name>navaho</name>
  </language>
  <language>
    <code>nwc</code>
    <name>klasični nevari</name>
  </language>
  <language>
    <code>ny</code>
    <name>njanja</name>
  </language>
  <language>
    <code>nym</code>
    <name>njamvezi</name>
  </language>
  <language>
    <code>nyn</code>
    <name>njankole</name>
  </language>
  <language>
    <code>nyo</code>
    <name>njoro</name>
  </language>
  <language>
    <code>nzi</code>
    <name>nzima</name>
  </language>
  <language>
    <code>oc</code>
    <name>provansalski</name>
  </language>
  <language>
    <code>oj</code>
    <name>ojibva</name>
  </language>
  <language>
    <code>om</code>
    <name>oromo</name>
  </language>
  <language>
    <code>or</code>
    <name>orijski</name>
  </language>
  <language>
    <code>os</code>
    <name>osetski</name>
  </language>
  <language>
    <code>osa</code>
    <name>osage</name>
  </language>
  <language>
    <code>ota</code>
    <name>otomanski turski</name>
  </language>
  <language>
    <code>oto</code>
    <name>otomanski jezik</name>
  </language>
  <language>
    <code>pa</code>
    <name>pandžabski</name>
  </language>
  <language>
    <code>paa</code>
    <name>papuanski jezik</name>
  </language>
  <language>
    <code>pag</code>
    <name>pangasinski</name>
  </language>
  <language>
    <code>pal</code>
    <name>pahlavi</name>
  </language>
  <language>
    <code>pam</code>
    <name>pampanga</name>
  </language>
  <language>
    <code>pap</code>
    <name>papiamento</name>
  </language>
  <language>
    <code>pau</code>
    <name>palauanski</name>
  </language>
  <language>
    <code>peo</code>
    <name>staropersijski</name>
  </language>
  <language>
    <code>phi</code>
    <name>filipinski jezik</name>
  </language>
  <language>
    <code>phn</code>
    <name>feničanski</name>
  </language>
  <language>
    <code>pi</code>
    <name>pali</name>
  </language>
  <language>
    <code>pl</code>
    <name>poljski</name>
  </language>
  <language>
    <code>pon</code>
    <name>ponpejski</name>
  </language>
  <language>
    <code>pra</code>
    <name>prakritski jezik</name>
  </language>
  <language>
    <code>pro</code>
    <name>staroprovansalski</name>
  </language>
  <language>
    <code>ps</code>
    <name>paštunski</name>
  </language>
  <language>
    <code>pt</code>
    <name>portugalski</name>
  </language>
  <language>
    <code>qu</code>
    <name>kvenča</name>
  </language>
  <language>
    <code>raj</code>
    <name>rađastani</name>
  </language>
  <language>
    <code>rap</code>
    <name>rapanui</name>
  </language>
  <language>
    <code>rar</code>
    <name>rarotongan</name>
  </language>
  <language>
    <code>rm</code>
    <name>reto-romanski</name>
  </language>
  <language>
    <code>rn</code>
    <name>rundi</name>
  </language>
  <language>
    <code>ro</code>
    <name>rumunski</name>
  </language>
  <language>
    <code>roa</code>
    <name>romanski jezik</name>
  </language>
  <language>
    <code>rom</code>
    <name>romani</name>
  </language>
  <language>
    <code>root</code>
    <name>run</name>
  </language>
  <language>
    <code>ru</code>
    <name>ruski</name>
  </language>
  <language>
    <code>rup</code>
    <name>aromanijski</name>
  </language>
  <language>
    <code>rw</code>
    <name>kinjarvanda</name>
  </language>
  <language>
    <code>sa</code>
    <name>sanskrit</name>
  </language>
  <language>
    <code>sad</code>
    <name>sandave</name>
  </language>
  <language>
    <code>sah</code>
    <name>jakut</name>
  </language>
  <language>
    <code>sai</code>
    <name>jezik južno-američkih indijanaca</name>
  </language>
  <language>
    <code>sal</code>
    <name>sališanski jezik</name>
  </language>
  <language>
    <code>sam</code>
    <name>samaritanski aramejski</name>
  </language>
  <language>
    <code>sas</code>
    <name>sasak</name>
  </language>
  <language>
    <code>sat</code>
    <name>santali</name>
  </language>
  <language>
    <code>sc</code>
    <name>sardinijski</name>
  </language>
  <language>
    <code>scn</code>
    <name>sicilijanski</name>
  </language>
  <language>
    <code>sco</code>
    <name>škotski</name>
  </language>
  <language>
    <code>sd</code>
    <name>sindi</name>
  </language>
  <language>
    <code>se</code>
    <name>severni sami</name>
  </language>
  <language>
    <code>sel</code>
    <name>selkap</name>
  </language>
  <language>
    <code>sem</code>
    <name>semitski jezik</name>
  </language>
  <language>
    <code>sg</code>
    <name>sango</name>
  </language>
  <language>
    <code>sga</code>
    <name>staroirski</name>
  </language>
  <language>
    <code>sgn</code>
    <name>jezik znakova</name>
  </language>
  <language>
    <code>sh</code>
    <name>srpskohrvatski</name>
  </language>
  <language>
    <code>shn</code>
    <name>šan</name>
  </language>
  <language>
    <code>si</code>
    <name>singaleski</name>
  </language>
  <language>
    <code>sid</code>
    <name>sidamo</name>
  </language>
  <language>
    <code>sio</code>
    <name>siuanski jezik</name>
  </language>
  <language>
    <code>sit</code>
    <name>sino-tibetanski jezik</name>
  </language>
  <language>
    <code>sk</code>
    <name>slovački</name>
  </language>
  <language>
    <code>sl</code>
    <name>slovenački</name>
  </language>
  <language>
    <code>sla</code>
    <name>slovenski jezik</name>
  </language>
  <language>
    <code>sm</code>
    <name>samoanski</name>
  </language>
  <language>
    <code>sma</code>
    <name>južni sami</name>
  </language>
  <language>
    <code>smi</code>
    <name>sami jezik</name>
  </language>
  <language>
    <code>smj</code>
    <name>lule sami</name>
  </language>
  <language>
    <code>smn</code>
    <name>inari sami</name>
  </language>
  <language>
    <code>sms</code>
    <name>skoltski jezik</name>
  </language>
  <language>
    <code>sn</code>
    <name>šona</name>
  </language>
  <language>
    <code>snk</code>
    <name>soninke</name>
  </language>
  <language>
    <code>so</code>
    <name>somalski</name>
  </language>
  <language>
    <code>sog</code>
    <name>sodžijenski</name>
  </language>
  <language>
    <code>son</code>
    <name>songai</name>
  </language>
  <language>
    <code>sq</code>
    <name>albanski</name>
  </language>
  <language>
    <code>sr</code>
    <name>srpski</name>
  </language>
  <language>
    <code>srn</code>
    <name>srananski tongo</name>
  </language>
  <language>
    <code>srr</code>
    <name>serer</name>
  </language>
  <language>
    <code>ss</code>
    <name>svati</name>
  </language>
  <language>
    <code>ssa</code>
    <name>nilo-saharski jezik</name>
  </language>
  <language>
    <code>st</code>
    <name>sesoto</name>
  </language>
  <language>
    <code>su</code>
    <name>sudanski</name>
  </language>
  <language>
    <code>suk</code>
    <name>sukuma</name>
  </language>
  <language>
    <code>sus</code>
    <name>susu</name>
  </language>
  <language>
    <code>sux</code>
    <name>sumerski</name>
  </language>
  <language>
    <code>sv</code>
    <name>švedski</name>
  </language>
  <language>
    <code>sw</code>
    <name>svahili</name>
  </language>
  <language>
    <code>swb</code>
    <name>komorski</name>
  </language>
  <language>
    <code>syc</code>
    <name>klasični sirijski</name>
  </language>
  <language>
    <code>syr</code>
    <name>sirijski</name>
  </language>
  <language>
    <code>ta</code>
    <name>tamilski</name>
  </language>
  <language>
    <code>tai</code>
    <name>tai jezik</name>
  </language>
  <language>
    <code>te</code>
    <name>telugu</name>
  </language>
  <language>
    <code>tem</code>
    <name>timne</name>
  </language>
  <language>
    <code>ter</code>
    <name>tereno</name>
  </language>
  <language>
    <code>tet</code>
    <name>tetum</name>
  </language>
  <language>
    <code>tg</code>
    <name>tađik</name>
  </language>
  <language>
    <code>th</code>
    <name>tajlandski</name>
  </language>
  <language>
    <code>ti</code>
    <name>tigrinja</name>
  </language>
  <language>
    <code>tig</code>
    <name>tigre</name>
  </language>
  <language>
    <code>tiv</code>
    <name>tiv</name>
  </language>
  <language>
    <code>tk</code>
    <name>turkmenski</name>
  </language>
  <language>
    <code>tkl</code>
    <name>tokelau</name>
  </language>
  <language>
    <code>tl</code>
    <name>tagalski</name>
  </language>
  <language>
    <code>tlh</code>
    <name>klingonski</name>
  </language>
  <language>
    <code>tli</code>
    <name>tlingit</name>
  </language>
  <language>
    <code>tmh</code>
    <name>tamašek</name>
  </language>
  <language>
    <code>tn</code>
    <name>tsvana</name>
  </language>
  <language>
    <code>to</code>
    <name>tonga</name>
  </language>
  <language>
    <code>tog</code>
    <name>njasa tonga</name>
  </language>
  <language>
    <code>tpi</code>
    <name>tok pisin</name>
  </language>
  <language>
    <code>tr</code>
    <name>turski</name>
  </language>
  <language>
    <code>ts</code>
    <name>tsonga</name>
  </language>
  <language>
    <code>tsi</code>
    <name>tsimšian</name>
  </language>
  <language>
    <code>tt</code>
    <name>tatarski</name>
  </language>
  <language>
    <code>tum</code>
    <name>tumbuka</name>
  </language>
  <language>
    <code>tup</code>
    <name>tupi jezik</name>
  </language>
  <language>
    <code>tut</code>
    <name>altaički jezik</name>
  </language>
  <language>
    <code>tvl</code>
    <name>tuvalu</name>
  </language>
  <language>
    <code>tw</code>
    <name>tvi</name>
  </language>
  <language>
    <code>ty</code>
    <name>tahićanski</name>
  </language>
  <language>
    <code>tyv</code>
    <name>tuvinijski</name>
  </language>
  <language>
    <code>udm</code>
    <name>udmurt</name>
  </language>
  <language>
    <code>ug</code>
    <name>ujgurski</name>
  </language>
  <language>
    <code>uga</code>
    <name>ugaritski</name>
  </language>
  <language>
    <code>uk</code>
    <name>ukrajinski</name>
  </language>
  <language>
    <code>umb</code>
    <name>umbundu</name>
  </language>
  <language>
    <code>und</code>
    <name>nepoznati ili nevažeći jezik</name>
  </language>
  <language>
    <code>ur</code>
    <name>urdu</name>
  </language>
  <language>
    <code>uz</code>
    <name>uzbečki</name>
  </language>
  <language>
    <code>vai</code>
    <name>vai</name>
  </language>
  <language>
    <code>ve</code>
    <name>venda</name>
  </language>
  <language>
    <code>vi</code>
    <name>vijetnamski</name>
  </language>
  <language>
    <code>vo</code>
    <name>volapük</name>
  </language>
  <language>
    <code>vot</code>
    <name>votski</name>
  </language>
  <language>
    <code>wa</code>
    <name>valun</name>
  </language>
  <language>
    <code>wak</code>
    <name>vakašanski jezik</name>
  </language>
  <language>
    <code>wal</code>
    <name>valamo</name>
  </language>
  <language>
    <code>war</code>
    <name>varej</name>
  </language>
  <language>
    <code>was</code>
    <name>vašo</name>
  </language>
  <language>
    <code>wen</code>
    <name>sorbijanski jezik</name>
  </language>
  <language>
    <code>wo</code>
    <name>volof</name>
  </language>
  <language>
    <code>xal</code>
    <name>kalmik</name>
  </language>
  <language>
    <code>xh</code>
    <name>khosa</name>
  </language>
  <language>
    <code>yao</code>
    <name>jao</name>
  </language>
  <language>
    <code>yap</code>
    <name>japeški</name>
  </language>
  <language>
    <code>yi</code>
    <name>jidiš</name>
  </language>
  <language>
    <code>yo</code>
    <name>jorubanski</name>
  </language>
  <language>
    <code>ypk</code>
    <name>jupik</name>
  </language>
  <language>
    <code>yue</code>
    <name>kantonski</name>
  </language>
  <language>
    <code>za</code>
    <name>zuang</name>
  </language>
  <language>
    <code>zap</code>
    <name>zapotečki</name>
  </language>
  <language>
    <code>zbl</code>
    <name>blisimboli</name>
  </language>
  <language>
    <code>zen</code>
    <name>zenaga</name>
  </language>
  <language>
    <code>zh</code>
    <name>kineski</name>
  </language>
  <language>
    <code>zh_Hans</code>
    <name>kineski (pojednostavljen)</name>
  </language>
  <language>
    <code>zh_Hant</code>
    <name>kineski (tradicionalni)</name>
  </language>
  <language>
    <code>znd</code>
    <name>zande</name>
  </language>
  <language>
    <code>zu</code>
    <name>zulu</name>
  </language>
  <language>
    <code>zun</code>
    <name>zuni</name>
  </language>
  <language>
    <code>zxx</code>
    <name>bez lingvističkog sadržaja</name>
  </language>
  <language>
    <code>zza</code>
    <name>zaza</name>
  </language>
</languages>
