<?xml version="1.0" encoding="utf-8"?>
<languages>
  <language>
    <code>ak</code>
    <name>akaŋ</name>
  </language>
  <language>
    <code>am</code>
    <name>amharik</name>
  </language>
  <language>
    <code>ar</code>
    <name>arabiya</name>
  </language>
  <language>
    <code>be</code>
    <name>belarussiya</name>
  </language>
  <language>
    <code>bg</code>
    <name>bulgaria</name>
  </language>
  <language>
    <code>bn</code>
    <name>bengalia</name>
  </language>
  <language>
    <code>cs</code>
    <name>syekya</name>
  </language>
  <language>
    <code>de</code>
    <name>germaŋ</name>
  </language>
  <language>
    <code>el</code>
    <name>grek</name>
  </language>
  <language>
    <code>en</code>
    <name>zah Anglofoŋ</name>
  </language>
  <language>
    <code>es</code>
    <name>Espaniya</name>
  </language>
  <language>
    <code>fa</code>
    <name>Persia</name>
  </language>
  <language>
    <code>fr</code>
    <name>zah sǝr Franssǝ</name>
  </language>
  <language>
    <code>ha</code>
    <name>haussa</name>
  </language>
  <language>
    <code>hi</code>
    <name>hindi</name>
  </language>
  <language>
    <code>hu</code>
    <name>hungariya</name>
  </language>
  <language>
    <code>id</code>
    <name>indonesiya</name>
  </language>
  <language>
    <code>ig</code>
    <name>igbo</name>
  </language>
  <language>
    <code>it</code>
    <name>italiya</name>
  </language>
  <language>
    <code>ja</code>
    <name>zah sǝr Japoŋ</name>
  </language>
  <language>
    <code>jv</code>
    <name>javaniya</name>
  </language>
  <language>
    <code>km</code>
    <name>kmer</name>
  </language>
  <language>
    <code>ko</code>
    <name>korea</name>
  </language>
  <language>
    <code>ms</code>
    <name>malasiya</name>
  </language>
  <language>
    <code>mua</code>
    <name>MUNDAŊ</name>
  </language>
  <language>
    <code>my</code>
    <name>birmania</name>
  </language>
  <language>
    <code>ne</code>
    <name>Nepaliya</name>
  </language>
  <language>
    <code>nl</code>
    <name>zah sǝr ma kasǝŋ</name>
  </language>
  <language>
    <code>pa</code>
    <name>Pǝnjabi</name>
  </language>
  <language>
    <code>pl</code>
    <name>Poloniya</name>
  </language>
  <language>
    <code>pt</code>
    <name>Zah sǝr Portugal</name>
  </language>
  <language>
    <code>ro</code>
    <name>Romaniya</name>
  </language>
  <language>
    <code>ru</code>
    <name>Russiya</name>
  </language>
  <language>
    <code>rw</code>
    <name>Zah sǝr Rwanda</name>
  </language>
  <language>
    <code>so</code>
    <name>Somaliya</name>
  </language>
  <language>
    <code>sv</code>
    <name>Swedia</name>
  </language>
  <language>
    <code>ta</code>
    <name>Tamul</name>
  </language>
  <language>
    <code>th</code>
    <name>Tai</name>
  </language>
  <language>
    <code>tr</code>
    <name>Turk</name>
  </language>
  <language>
    <code>uk</code>
    <name>Ukrainia</name>
  </language>
  <language>
    <code>ur</code>
    <name>Urdu</name>
  </language>
  <language>
    <code>vi</code>
    <name>Vietnamiya</name>
  </language>
  <language>
    <code>yo</code>
    <name>Yoruba</name>
  </language>
  <language>
    <code>zh</code>
    <name>zah Syiŋ</name>
  </language>
  <language>
    <code>zu</code>
    <name>Zulu</name>
  </language>
</languages>
