<?xml version="1.0" encoding="utf-8"?>
<languages>
  <language>
    <code>ab</code>
    <name>Abčasiš</name>
  </language>
  <language>
    <code>af</code>
    <name>Afrikáns</name>
  </language>
  <language>
    <code>am</code>
    <name>Amhariš</name>
  </language>
  <language>
    <code>ar</code>
    <name>Arabiš</name>
  </language>
  <language>
    <code>as</code>
    <name>Assamesiš</name>
  </language>
  <language>
    <code>ay</code>
    <name>Aymara</name>
  </language>
  <language>
    <code>az</code>
    <name>Serbaidšaniš</name>
  </language>
  <language>
    <code>be</code>
    <name>Wísrussiš</name>
  </language>
  <language>
    <code>bg</code>
    <name>Bulgariš</name>
  </language>
  <language>
    <code>bn</code>
    <name>Bengališ</name>
  </language>
  <language>
    <code>bo</code>
    <name>Tibetiš</name>
  </language>
  <language>
    <code>bs</code>
    <name>Bosniš</name>
  </language>
  <language>
    <code>ca</code>
    <name>Katalaniš</name>
  </language>
  <language>
    <code>cs</code>
    <name>Tšečiš</name>
  </language>
  <language>
    <code>cy</code>
    <name>Walisiš</name>
  </language>
  <language>
    <code>da</code>
    <name>Däniš</name>
  </language>
  <language>
    <code>de</code>
    <name>Titš</name>
  </language>
  <language>
    <code>de_AT</code>
    <name>Öštričišes Titš</name>
  </language>
  <language>
    <code>de_CH</code>
    <name>Schwizer Hočtitš</name>
  </language>
  <language>
    <code>dv</code>
    <name>Malediwiš</name>
  </language>
  <language>
    <code>dz</code>
    <name>Butaniš</name>
  </language>
  <language>
    <code>efi</code>
    <name>Efik</name>
  </language>
  <language>
    <code>el</code>
    <name>Gričiš</name>
  </language>
  <language>
    <code>en</code>
    <name>Engliš</name>
  </language>
  <language>
    <code>en_AU</code>
    <name>Auštrališes Engliš</name>
  </language>
  <language>
    <code>en_CA</code>
    <name>Kanadišes Engliš</name>
  </language>
  <language>
    <code>en_GB</code>
    <name>Britišes Engliš</name>
  </language>
  <language>
    <code>en_US</code>
    <name>Amerikanišes Engliš</name>
  </language>
  <language>
    <code>es</code>
    <name>Schpaniš</name>
  </language>
  <language>
    <code>es_419</code>
    <name>Latiamerikanišes Schpaniš</name>
  </language>
  <language>
    <code>es_ES</code>
    <name>Iberišes Schpaniš</name>
  </language>
  <language>
    <code>et</code>
    <name>Estniš</name>
  </language>
  <language>
    <code>eu</code>
    <name>Baskiš</name>
  </language>
  <language>
    <code>fa</code>
    <name>Persiš</name>
  </language>
  <language>
    <code>fi</code>
    <name>Finiš</name>
  </language>
  <language>
    <code>fil</code>
    <name>Filipiniš</name>
  </language>
  <language>
    <code>fj</code>
    <name>Fidšianiš</name>
  </language>
  <language>
    <code>fr</code>
    <name>Wälš</name>
  </language>
  <language>
    <code>fr_CA</code>
    <name>Kanadišes Wälš</name>
  </language>
  <language>
    <code>fr_CH</code>
    <name>Schwizer Wälš</name>
  </language>
  <language>
    <code>ga</code>
    <name>Iriš</name>
  </language>
  <language>
    <code>gl</code>
    <name>Galiziš</name>
  </language>
  <language>
    <code>gn</code>
    <name>Guarani</name>
  </language>
  <language>
    <code>gu</code>
    <name>Gujarati</name>
  </language>
  <language>
    <code>ha</code>
    <name>Hausa</name>
  </language>
  <language>
    <code>haw</code>
    <name>Hawaíaniš</name>
  </language>
  <language>
    <code>he</code>
    <name>Hebräiš</name>
  </language>
  <language>
    <code>hi</code>
    <name>Hindi</name>
  </language>
  <language>
    <code>hr</code>
    <name>Kroatiš</name>
  </language>
  <language>
    <code>ht</code>
    <name>Haitianiš</name>
  </language>
  <language>
    <code>hu</code>
    <name>Ungariš</name>
  </language>
  <language>
    <code>hy</code>
    <name>Armeniš</name>
  </language>
  <language>
    <code>id</code>
    <name>Indonesiš</name>
  </language>
  <language>
    <code>ig</code>
    <name>Igbo</name>
  </language>
  <language>
    <code>is</code>
    <name>Iisländiš</name>
  </language>
  <language>
    <code>it</code>
    <name>Italieniš</name>
  </language>
  <language>
    <code>ja</code>
    <name>Japaniš</name>
  </language>
  <language>
    <code>ka</code>
    <name>Georgiš</name>
  </language>
  <language>
    <code>kk</code>
    <name>Kazačiš</name>
  </language>
  <language>
    <code>km</code>
    <name>Kambodšaniš</name>
  </language>
  <language>
    <code>kn</code>
    <name>Kannada</name>
  </language>
  <language>
    <code>ko</code>
    <name>Koreaniš</name>
  </language>
  <language>
    <code>ks</code>
    <name>Kašmiriš</name>
  </language>
  <language>
    <code>ku</code>
    <name>Kurdiš</name>
  </language>
  <language>
    <code>ky</code>
    <name>Kirgisiš</name>
  </language>
  <language>
    <code>la</code>
    <name>Latiniš</name>
  </language>
  <language>
    <code>lb</code>
    <name>Luxemburgiš</name>
  </language>
  <language>
    <code>ln</code>
    <name>Lingala</name>
  </language>
  <language>
    <code>lo</code>
    <name>Laotiš</name>
  </language>
  <language>
    <code>lt</code>
    <name>Litauiš</name>
  </language>
  <language>
    <code>lv</code>
    <name>Lettiš</name>
  </language>
  <language>
    <code>mg</code>
    <name>Malagási</name>
  </language>
  <language>
    <code>mi</code>
    <name>Maori</name>
  </language>
  <language>
    <code>mk</code>
    <name>Mazedoniš</name>
  </language>
  <language>
    <code>ml</code>
    <name>Malayalam</name>
  </language>
  <language>
    <code>mn</code>
    <name>Mongoliš</name>
  </language>
  <language>
    <code>mr</code>
    <name>Marathi</name>
  </language>
  <language>
    <code>ms</code>
    <name>Malaíš</name>
  </language>
  <language>
    <code>mt</code>
    <name>Maltesiš</name>
  </language>
  <language>
    <code>my</code>
    <name>Burmesiš</name>
  </language>
  <language>
    <code>nb</code>
    <name>Norwegiš Bokmål</name>
  </language>
  <language>
    <code>nd</code>
    <name>Nordndebele</name>
  </language>
  <language>
    <code>ne</code>
    <name>Nepalesiš</name>
  </language>
  <language>
    <code>nl</code>
    <name>Holändiš</name>
  </language>
  <language>
    <code>nl_BE</code>
    <name>Flämiš</name>
  </language>
  <language>
    <code>nn</code>
    <name>Norwegiš Nynorsk</name>
  </language>
  <language>
    <code>nso</code>
    <name>Nordsotho</name>
  </language>
  <language>
    <code>ny</code>
    <name>Nyanja</name>
  </language>
  <language>
    <code>or</code>
    <name>Oriya</name>
  </language>
  <language>
    <code>os</code>
    <name>Osétiš</name>
  </language>
  <language>
    <code>pa</code>
    <name>Pandšabiš</name>
  </language>
  <language>
    <code>pl</code>
    <name>Polniš</name>
  </language>
  <language>
    <code>ps</code>
    <name>Paštu</name>
  </language>
  <language>
    <code>pt</code>
    <name>Portugisiš</name>
  </language>
  <language>
    <code>pt_BR</code>
    <name>Brasilianišes Portugisiš</name>
  </language>
  <language>
    <code>pt_PT</code>
    <name>Iberišes Portugisiš</name>
  </language>
  <language>
    <code>qu</code>
    <name>Quečua</name>
  </language>
  <language>
    <code>rm</code>
    <name>Rätromaniš</name>
  </language>
  <language>
    <code>rn</code>
    <name>Rundi</name>
  </language>
  <language>
    <code>ro</code>
    <name>Rumäniš</name>
  </language>
  <language>
    <code>ru</code>
    <name>Rusiš</name>
  </language>
  <language>
    <code>rw</code>
    <name>Ruandiš</name>
  </language>
  <language>
    <code>sa</code>
    <name>Sanskrit</name>
  </language>
  <language>
    <code>sah</code>
    <name>Jakutiš</name>
  </language>
  <language>
    <code>sd</code>
    <name>Sindhi</name>
  </language>
  <language>
    <code>se</code>
    <name>Nordsamiš</name>
  </language>
  <language>
    <code>sg</code>
    <name>Sango</name>
  </language>
  <language>
    <code>si</code>
    <name>Singalesiš</name>
  </language>
  <language>
    <code>sk</code>
    <name>Slowakiš</name>
  </language>
  <language>
    <code>sl</code>
    <name>Sloweniš</name>
  </language>
  <language>
    <code>sm</code>
    <name>Samoaniš</name>
  </language>
  <language>
    <code>sn</code>
    <name>Shona</name>
  </language>
  <language>
    <code>so</code>
    <name>Somališ</name>
  </language>
  <language>
    <code>sq</code>
    <name>Albaniš</name>
  </language>
  <language>
    <code>sr</code>
    <name>Serbiš</name>
  </language>
  <language>
    <code>ss</code>
    <name>Swazi</name>
  </language>
  <language>
    <code>st</code>
    <name>Südsotho</name>
  </language>
  <language>
    <code>su</code>
    <name>Sundanesiš</name>
  </language>
  <language>
    <code>sv</code>
    <name>Schwediš</name>
  </language>
  <language>
    <code>sw</code>
    <name>Suaheliš</name>
  </language>
  <language>
    <code>ta</code>
    <name>Tamiliš</name>
  </language>
  <language>
    <code>te</code>
    <name>Telugu</name>
  </language>
  <language>
    <code>tet</code>
    <name>Tetum</name>
  </language>
  <language>
    <code>tg</code>
    <name>Tadšikiš</name>
  </language>
  <language>
    <code>th</code>
    <name>Thailändiš</name>
  </language>
  <language>
    <code>ti</code>
    <name>Tigrinja</name>
  </language>
  <language>
    <code>tk</code>
    <name>Turkmeniš</name>
  </language>
  <language>
    <code>tn</code>
    <name>Tswana</name>
  </language>
  <language>
    <code>to</code>
    <name>Tonga</name>
  </language>
  <language>
    <code>tpi</code>
    <name>Niwmelanesiš</name>
  </language>
  <language>
    <code>tr</code>
    <name>Türkiš</name>
  </language>
  <language>
    <code>ts</code>
    <name>Tsonga</name>
  </language>
  <language>
    <code>ty</code>
    <name>Taitiš</name>
  </language>
  <language>
    <code>ug</code>
    <name>Uiguriš</name>
  </language>
  <language>
    <code>uk</code>
    <name>Ukrainiš</name>
  </language>
  <language>
    <code>und</code>
    <name>Unbekannti Schprač</name>
  </language>
  <language>
    <code>ur</code>
    <name>Urdu</name>
  </language>
  <language>
    <code>uz</code>
    <name>Usbekiš</name>
  </language>
  <language>
    <code>ve</code>
    <name>Venda</name>
  </language>
  <language>
    <code>vi</code>
    <name>Vietnamesiš</name>
  </language>
  <language>
    <code>wae</code>
    <name>Walser</name>
  </language>
  <language>
    <code>wo</code>
    <name>Wolof</name>
  </language>
  <language>
    <code>xh</code>
    <name>Xhosa</name>
  </language>
  <language>
    <code>yo</code>
    <name>Yoruba</name>
  </language>
  <language>
    <code>zh</code>
    <name>Chinesiš</name>
  </language>
  <language>
    <code>zh_Hans</code>
    <name>Vereifačts Chinesiš</name>
  </language>
  <language>
    <code>zh_Hant</code>
    <name>Traditionells Chinesiš</name>
  </language>
  <language>
    <code>zu</code>
    <name>Zulu</name>
  </language>
</languages>
